{
  "timestamp": "2025-08-06T15:17:35.573930",
  "filepath": "intelligent_captures/successful/success_20250806_151735_unknown_object.jpg",
  "recognition": {
    "label": "unknown_object",
    "confidence": 0.6666666666666666,
    "is_known": true,
    "all_scores": {
      "apple": 0.0,
      "banana": 0.0,
      "cat": 0.3333333333333333,
      "test_banana": 0.0,
      "unknown_object": 0.6666666666666666
    }
  },
  "yolo_detections": [
    {
      "class_name": "banana",
      "confidence": 0.6144706010818481,
      "bbox": [
        749,
        1,
        526,
        515
      ]
    }
  ],
  "stats": {
    "frames_processed": 5515,
    "triggers_fired": 22,
    "successful_recognitions": 22,
    "failed_recognitions": 0,
    "gemini_queries": 0,
    "knn_updates": 0
  }
}